[{"code": "aa", "name": "Den Helder"}, {"code": "ab", "name": "Sittard-Geleen"}, {"code": "ac", "name": "Enkhuizen"}, {"code": "ad", "name": "Bernheze"}, {"code": "ae", "name": "Koggenland"}, {"code": "af", "name": "De Ronde Venen"}, {"code": "ag", "name": "IJsselstein"}, {"code": "ah", "name": "Aalsmeer"}, {"code": "ai", "name": "Deurne"}, {"code": "aj", "name": "Baarle-Nassau"}, {"code": "ak", "name": "Gooise Meren"}, {"code": "al", "name": "Buren"}, {"code": "am", "name": "Weststellingwerf"}, {"code": "an", "name": "Veldhoven"}, {"code": "ao", "name": "Tynaarlo"}, {"code": "ap", "name": "De Friese Meren"}, {"code": "aq", "name": "Peel en Maas"}, {"code": "ar", "name": "Oegstgeest"}, {"code": "as", "name": "Reimerswaal"}, {"code": "at", "name": "Wierden"}, {"code": "au", "name": "Voorne aan Zee"}, {"code": "av", "name": "Montfoort"}, {"code": "aw", "name": "Brummen"}, {"code": "ax", "name": "Diemen"}, {"code": "ay", "name": "Barneveld"}, {"code": "az", "name": "Uitgeest"}, {"code": "ba", "name": "Landsmeer"}, {"code": "bb", "name": "Ommen"}, {"code": "bc", "name": "Hardinxveld-Giessendam"}, {"code": "bd", "name": "Houten"}, {"code": "be", "name": "Schiermonnikoog"}, {"code": "bf", "name": "Stein"}, {"code": "bg", "name": "Pijnacker-Nootdorp"}, {"code": "bh", "name": "Hollands Kroon"}, {"code": "bi", "name": "Bergeijk"}, {"code": "bj", "name": "Veenendaal"}, {"code": "bk", "name": "Heemskerk"}, {"code": "bl", "name": "Krimpenerwaard"}, {"code": "bm", "name": "Noord-Beveland"}, {"code": "bn", "name": "Amstelveen"}, {"code": "bo", "name": "Emmen"}, {"code": "bp", "name": "Oldebroek"}, {"code": "bq", "name": "Noordwijk"}, {"code": "br", "name": "Bodegraven-Reeuwijk"}, {"code": "bs", "name": "Aalten"}, {"code": "bt", "name": "Doesburg"}, {"code": "bu", "name": "Bergen (Li)"}, {"code": "bv", "name": "Haarlem"}, {"code": "bw", "name": "Ridderkerk"}, {"code": "bx", "name": "Saba"}, {"code": "by", "name": "Arnhem"}, {"code": "bz", "name": "Wijk bij Duurstede"}, {"code": "ca", "name": "Beuningen"}, {"code": "cb", "name": "Lopik"}, {"code": "cc", "name": "Lisse"}, {"code": "cd", "name": "Rijswijk"}, {"code": "ce", "name": "Waddinxveen"}, {"code": "cf", "name": "Beek"}, {"code": "cg", "name": "Achtkarspelen"}, {"code": "ch", "name": "Veere"}, {"code": "ci", "name": "Zaltbommel"}, {"code": "cj", "name": "Neder-Betuwe"}, {"code": "ck", "name": "Middelburg"}, {"code": "cl", "name": "De Bilt"}, {"code": "cm", "name": "Leiderdorp"}, {"code": "cn", "name": "Oude IJsselstreek"}, {"code": "co", "name": "Waadhoeke"}, {"code": "cp", "name": "Hattem"}, {"code": "cq", "name": "Zwolle"}, {"code": "cr", "name": "Opsterland"}, {"code": "cs", "name": "Hof van Twente"}, {"code": "ct", "name": "Dronten"}, {"code": "cu", "name": "Helmond"}, {"code": "cv", "name": "Eindhoven"}, {"code": "cw", "name": "Venlo"}, {"code": "cx", "name": "Geertruidenberg"}, {"code": "cy", "name": "Westerwolde"}, {"code": "cz", "name": "Oudewater"}, {"code": "da", "name": "Meppel"}, {"code": "db", "name": "Alphen aan den Rijn"}, {"code": "dc", "name": "Heemstede"}, {"code": "dd", "name": "Belgi\u00eb"}, {"code": "de", "name": "Vught"}, {"code": "df", "name": "'s-Hertogenbosch"}, {"code": "dg", "name": "Eersel"}, {"code": "dh", "name": "West Betuwe"}, {"code": "di", "name": "Kaag en Braassem"}, {"code": "dj", "name": "Sluis"}, {"code": "dk", "name": "Noardeast-Frysl\u00e2n"}, {"code": "dl", "name": "Loon op Zand"}, {"code": "dm", "name": "Haaksbergen"}, {"code": "dn", "name": "Dongen"}, {"code": "do", "name": "Son en Breugel"}, {"code": "dp", "name": "Altena"}, {"code": "dq", "name": "Maashorst"}, {"code": "dr", "name": "Land van Cuijk"}, {"code": "ds", "name": "Uithoorn"}, {"code": "dt", "name": "Hillegom"}, {"code": "du", "name": "Losser"}, {"code": "dv", "name": "Maastricht"}, {"code": "dw", "name": "Sint Eustatius"}, {"code": "dx", "name": "Meerssen"}, {"code": "dy", "name": "Gennep"}, {"code": "dz", "name": "Opmeer"}, {"code": "ea", "name": "Beekdaelen"}, {"code": "eb", "name": "Wormerland"}, {"code": "ec", "name": "Hoogeveen"}, {"code": "ed", "name": "Terschelling"}, {"code": "ee", "name": "Gouda"}, {"code": "ef", "name": "Mook en Middelaar"}, {"code": "eg", "name": "Duiven"}, {"code": "eh", "name": "Amersfoort"}, {"code": "ei", "name": "Kerkrade"}, {"code": "ej", "name": "Voorschoten"}, {"code": "ek", "name": "Smallingerland"}, {"code": "el", "name": "Deventer"}, {"code": "em", "name": "Alkmaar"}, {"code": "en", "name": "Dalfsen"}, {"code": "eo", "name": "Vlissingen"}, {"code": "ep", "name": "Zevenaar"}, {"code": "eq", "name": "Heiloo"}, {"code": "er", "name": "Katwijk"}, {"code": "es", "name": "Ermelo"}, {"code": "et", "name": "Dinkelland"}, {"code": "eu", "name": "Waalwijk"}, {"code": "ev", "name": "Eijsden-Margraten"}, {"code": "ew", "name": "Nuenen, Gerwen en Nederwetten"}, {"code": "ex", "name": "Ede"}, {"code": "ey", "name": "Staphorst"}, {"code": "ez", "name": "Epe"}, {"code": "fa", "name": "Renswoude"}, {"code": "fb", "name": "Montferland"}, {"code": "fc", "name": "Kampen"}, {"code": "fd", "name": "Beesel"}, {"code": "fe", "name": "Tilburg"}, {"code": "ff", "name": "Wassenaar"}, {"code": "fg", "name": "Albrandswaard"}, {"code": "fh", "name": "Lelystad"}, {"code": "fi", "name": "Nijkerk"}, {"code": "fj", "name": "Dantumadeel"}, {"code": "fk", "name": "Zeist"}, {"code": "fl", "name": "Terneuzen"}, {"code": "fm", "name": "Lochem"}, {"code": "fn", "name": "Gilze en Rijen"}, {"code": "fo", "name": "Cranendonck"}, {"code": "fp", "name": "Stadskanaal"}, {"code": "fq", "name": "Amsterdam"}, {"code": "fr", "name": "Wageningen"}, {"code": "fs", "name": "Bunschoten"}, {"code": "ft", "name": "Noordenveld"}, {"code": "fu", "name": "Haarlemmermeer"}, {"code": "fv", "name": "Laren"}, {"code": "fw", "name": "Beverwijk"}, {"code": "fx", "name": "Pekela"}, {"code": "fy", "name": "Schouwen-Duiveland"}, {"code": "fz", "name": "Borsele"}, {"code": "ga", "name": "Utrechtse Heuvelrug"}, {"code": "gb", "name": "Borger-Odoorn"}, {"code": "gc", "name": "Oldambt"}, {"code": "gd", "name": "Geldrop-Mierlo"}, {"code": "ge", "name": "Heerde"}, {"code": "gf", "name": "Winterswijk"}, {"code": "gg", "name": "Barendrecht"}, {"code": "gh", "name": "Lansingerland"}, {"code": "gi", "name": "Zandvoort"}, {"code": "gj", "name": "Woensdrecht"}, {"code": "gk", "name": "Westerveld"}, {"code": "gl", "name": "Oostzaan"}, {"code": "gm", "name": "Oss"}, {"code": "gn", "name": "Bergen op Zoom"}, {"code": "go", "name": "Brunssum"}, {"code": "gp", "name": "Krimpen aan den IJssel"}, {"code": "gq", "name": "Goes"}, {"code": "gr", "name": "West Maas en Waal"}, {"code": "gs", "name": "Aa en Hunze"}, {"code": "gt", "name": "Leiden"}, {"code": "gu", "name": "Purmerend"}, {"code": "gv", "name": "Ameland"}, {"code": "gw", "name": "Bloemendaal"}, {"code": "gx", "name": "Rijssen-Holten"}, {"code": "gy", "name": "Bladel"}, {"code": "gz", "name": "Horst aan de Maas"}, {"code": "ha", "name": "Waalre"}, {"code": "hb", "name": "Vijfheerenlanden"}, {"code": "hc", "name": "Castricum"}, {"code": "hd", "name": "Texel"}, {"code": "he", "name": "Eemsdelta"}, {"code": "hf", "name": "Renkum"}, {"code": "hg", "name": "Heeze-Leende"}, {"code": "hh", "name": "Bergen (NH)"}, {"code": "hi", "name": "Zundert"}, {"code": "hj", "name": "Teylingen"}, {"code": "hk", "name": "Hilvarenbeek"}, {"code": "hl", "name": "Culemborg"}, {"code": "hm", "name": "Leusden"}, {"code": "hn", "name": "Bronckhorst"}, {"code": "ho", "name": "Capelle aan den IJssel"}, {"code": "hp", "name": "Hulst"}, {"code": "hq", "name": "Urk"}, {"code": "hr", "name": "Echt-Susteren"}, {"code": "hs", "name": "Heumen"}, {"code": "ht", "name": "Woudenberg"}, {"code": "hu", "name": "Halderberge"}, {"code": "hv", "name": "Veendam"}, {"code": "hw", "name": "Maasdriel"}, {"code": "hx", "name": "Druten"}, {"code": "hy", "name": "Oosterhout"}, {"code": "hz", "name": "Rotterdam"}, {"code": "ia", "name": "Weert"}, {"code": "ib", "name": "Baarn"}, {"code": "ic", "name": "Raalte"}, {"code": "id", "name": "Leudal"}, {"code": "ie", "name": "Maassluis"}, {"code": "if", "name": "Oldenzaal"}, {"code": "ig", "name": "Roosendaal"}, {"code": "ih", "name": "Tholen"}, {"code": "ii", "name": "Kapelle"}, {"code": "ij", "name": "Nieuwegein"}, {"code": "ik", "name": "Boekel"}, {"code": "il", "name": "Ouder-Amstel"}, {"code": "im", "name": "Molenlanden"}, {"code": "in", "name": "Drechterland"}, {"code": "io", "name": "Rheden"}, {"code": "ip", "name": "Etten-Leur"}, {"code": "iq", "name": "Sliedrecht"}, {"code": "ir", "name": "Wijchen"}, {"code": "is", "name": "De Wolden"}, {"code": "it", "name": "Zwijndrecht"}, {"code": "iu", "name": "Oirschot"}, {"code": "iv", "name": "Valkenswaard"}, {"code": "iw", "name": "Hilversum"}, {"code": "ix", "name": "Wijdemeren"}, {"code": "iy", "name": "Zutphen"}, {"code": "iz", "name": "Vlieland"}, {"code": "ja", "name": "Medemblik"}, {"code": "jb", "name": "Breda"}, {"code": "jc", "name": "Den Haag"}, {"code": "jd", "name": "Assen"}, {"code": "je", "name": "Landgraaf"}, {"code": "jf", "name": "Roerdalen"}, {"code": "jg", "name": "Reusel-De Mierden"}, {"code": "jh", "name": "Zaanstad"}, {"code": "ji", "name": "Tietjerksteradeel"}, {"code": "jj", "name": "Oost Gelre"}, {"code": "jk", "name": "Berkelland"}, {"code": "jl", "name": "Woerden"}, {"code": "jm", "name": "Delft"}, {"code": "jn", "name": "Harlingen"}, {"code": "jo", "name": "Midden-Groningen"}, {"code": "jp", "name": "Westervoort"}, {"code": "jq", "name": "Rozendaal"}, {"code": "jr", "name": "Gorinchem"}, {"code": "js", "name": "Gulpen-Wittem"}, {"code": "jt", "name": "Zoetermeer"}, {"code": "ju", "name": "Olst-Wijhe"}, {"code": "jv", "name": "Tiel"}, {"code": "jw", "name": "Soest"}, {"code": "jx", "name": "Stichtse Vecht"}, {"code": "jy", "name": "Valkenburg aan de Geul"}, {"code": "jz", "name": "Rucphen"}, {"code": "ka", "name": "Nijmegen"}, {"code": "kb", "name": "Utrecht"}, {"code": "kc", "name": "Midden-Delfland"}, {"code": "kd", "name": "Vaals"}, {"code": "ke", "name": "Hendrik-Ido-Ambacht"}, {"code": "kf", "name": "Rhenen"}, {"code": "kg", "name": "Zoeterwoude"}, {"code": "kh", "name": "Berg en Dal"}, {"code": "ki", "name": "Heerenveen"}, {"code": "kj", "name": "Edam-Volendam"}, {"code": "kk", "name": "Leidschendam-Voorburg"}, {"code": "kl", "name": "Almere"}, {"code": "km", "name": "Apeldoorn"}, {"code": "kn", "name": "Gemert-Bakel"}, {"code": "ko", "name": "Het Hogeland"}, {"code": "kp", "name": "Waterland"}, {"code": "kq", "name": "Lingewaard"}, {"code": "kr", "name": "Heerlen"}, {"code": "ks", "name": "Heusden"}, {"code": "kt", "name": "Papendrecht"}, {"code": "ku", "name": "Boxtel"}, {"code": "kv", "name": "Schagen"}, {"code": "kw", "name": "Eemnes"}, {"code": "kx", "name": "Westerkwartier"}, {"code": "ky", "name": "Goirle"}, {"code": "kz", "name": "Sint-Michielsgestel"}, {"code": "la", "name": "Laarbeek"}, {"code": "lb", "name": "Coevorden"}, {"code": "lc", "name": "Leeuwarden"}, {"code": "ld", "name": "Nieuwkoop"}, {"code": "le", "name": "Best"}, {"code": "lf", "name": "Tubbergen"}, {"code": "lg", "name": "Steenwijkerland"}, {"code": "lh", "name": "Voerendaal"}, {"code": "li", "name": "Ooststellingwerf"}, {"code": "lj", "name": "Nissewaard"}, {"code": "lk", "name": "Dordrecht"}, {"code": "ll", "name": "Hengelo"}, {"code": "lm", "name": "Alphen-Chaam"}, {"code": "ln", "name": "Noordoostpolder"}, {"code": "lo", "name": "Scherpenzeel"}, {"code": "lp", "name": "Zeewolde"}, {"code": "lq", "name": "Oisterwijk"}, {"code": "lr", "name": "Hoeksche Waard"}, {"code": "ls", "name": "Stede Broec"}, {"code": "lt", "name": "Huizen"}, {"code": "lu", "name": "Doetinchem"}, {"code": "lv", "name": "Meierijstad"}, {"code": "lw", "name": "Steenbergen"}, {"code": "lx", "name": "Westland"}, {"code": "ly", "name": "Dijk en Waard"}, {"code": "lz", "name": "Moerdijk"}, {"code": "ma", "name": "Putten"}, {"code": "mb", "name": "Voorst"}, {"code": "mc", "name": "Harderwijk"}, {"code": "md", "name": "Schiedam"}, {"code": "me", "name": "Bonaire"}, {"code": "mf", "name": "Elburg"}, {"code": "mg", "name": "Maasgouw"}, {"code": "mh", "name": "Nunspeet"}, {"code": "mi", "name": "Midden-Drenthe"}, {"code": "mj", "name": "Drimmelen"}, {"code": "mk", "name": "Hellendoorn"}, {"code": "ml", "name": "Goeree-Overflakkee"}, {"code": "mm", "name": "Zuidplas"}, {"code": "mn", "name": "Borne"}, {"code": "mo", "name": "Bunnik"}, {"code": "mp", "name": "Alblasserdam"}, {"code": "mq", "name": "Vlaardingen"}, {"code": "mr", "name": "Venray"}, {"code": "ms", "name": "Velsen"}, {"code": "mt", "name": "Groningen"}, {"code": "mu", "name": "Enschede"}, {"code": "mv", "name": "Someren"}, {"code": "mw", "name": "S\u00fadwest-Frysl\u00e2n"}, {"code": "mx", "name": "Hardenberg"}, {"code": "my", "name": "Asten"}, {"code": "mz", "name": "Nederweert"}, {"code": "na", "name": "Blaricum"}, {"code": "nb", "name": "Roermond"}, {"code": "nc", "name": "Almelo"}, {"code": "nd", "name": "Zwartewaterland"}, {"code": "ne", "name": "Twenterand"}, {"code": "nf", "name": "Overbetuwe"}, {"code": "ng", "name": "Simpelveld"}, {"code": "nh", "name": "Hoorn"}]